montyhallsim.py
montyhallsim-1.0.1.dist-info/LICENSE
montyhallsim-1.0.1.dist-info/METADATA
montyhallsim-1.0.1.dist-info/WHEEL
montyhallsim-1.0.1.dist-info/entry_points.txt
montyhallsim-1.0.1.dist-info/top_level.txt
montyhallsim-1.0.1.dist-info/RECORD
