Metadata-Version: 2.1
Name: montyhallsim
Version: 1.0.1
Summary: A command-line interface for simulating the Monty Hall problem.
Home-page: https://github.com/mrwolferinc/montyhallsim
Author: mrwolferinc
Author-email: bluewolf153622@gmail.com
License: MIT
Keywords: montyhallsim,monty-hall-problem,montyhallproblem,monty-hall-problem-simulation,monty-hall-simulation,monty-hall-sim,cli
Platform: UNKNOWN
Classifier: License :: OSI Approved :: MIT License
Classifier: Programming Language :: Python
Classifier: Programming Language :: Python :: 3
Classifier: Programming Language :: Python :: 3.7
Classifier: Programming Language :: Python :: 3.8
Classifier: Programming Language :: Python :: 3.9
Classifier: Programming Language :: Python :: 3.10
Classifier: Operating System :: Microsoft :: Windows
Classifier: Operating System :: POSIX :: Linux
Requires-Python: >=3.7
